defaults/__init__.py
defaults/functions.py
defaults/settings.py
defaults/utils.py
defaults/wsgi.py
django_defaults-0.0.0.dist-info/DESCRIPTION.rst
django_defaults-0.0.0.dist-info/METADATA
django_defaults-0.0.0.dist-info/RECORD
django_defaults-0.0.0.dist-info/WHEEL
django_defaults-0.0.0.dist-info/metadata.json
django_defaults-0.0.0.dist-info/top_level.txt
