Metadata-Version: 2.0
Name: django-defaults
Version: 0.0.0
Summary: Django settings sans boilerplate
Home-page: https://github.com/mvasilkov/django-defaults
Author: Mark Vasilkov
Author-email: mvasilkov@gmail.com
License: MIT
Keywords: django settings toml
Platform: UNKNOWN
Classifier: Framework :: Django
Classifier: Intended Audience :: Developers
Classifier: License :: OSI Approved :: MIT License
Classifier: Programming Language :: Python :: 3
Classifier: Programming Language :: Python :: 3 :: Only
Classifier: Programming Language :: Python :: Implementation :: CPython
Requires-Dist: toml
